pewhits/__init__.py
pewhits/__main__.py
pewhits/models.py
pewhits-0.1.0.dist-info/METADATA
pewhits-0.1.0.dist-info/WHEEL
pewhits-0.1.0.dist-info/top_level.txt
pewhits-0.1.0.dist-info/RECORD
