Metadata-Version: 2.1
Name: pewhits
Version: 0.1.0
Summary: A Python client SDK for the PewHits radio server
Author-email: Chitransh Shrivastava <chitransh819@gmail.com>
License: MIT
Requires-Python: >=3.11
Requires-Dist: typing-extensions>=4.12.2
Requires-Dist: cattrs>=22.2.0
Requires-Dist: quattro>=22.2.0
Requires-Dist: attrs>=24.2.0
Requires-Dist: aiohttp>=3.10.5
